{
  "checksums": [
    {
      "id": "github_release/github.com/BurntSushi/ripgrep/15.1.0/ripgrep-15.1.0-aarch64-apple-darwin.tar.gz",
      "checksum": "378E973289176CA0C6054054EE7F631A065874A352BF43F0FA60EF079B6BA715",
      "algorithm": "sha256"
    },
    {
      "id": "github_release/github.com/BurntSushi/ripgrep/15.1.0/ripgrep-15.1.0-aarch64-unknown-linux-gnu.tar.gz",
      "checksum": "2B661C6EF508E902F388E9098D9C4C5ACA72C87B55922D94ABDBA830B4DC885E",
      "algorithm": "sha256"
    },
    {
      "id": "github_release/github.com/BurntSushi/ripgrep/15.1.0/ripgrep-15.1.0-x86_64-apple-darwin.tar.gz",
      "checksum": "64811CB24E77CAC3057D6C40B63AC9BECF9082EEDD54CA411B475B755D334882",
      "algorithm": "sha256"
    },
    {
      "id": "github_release/github.com/BurntSushi/ripgrep/15.1.0/ripgrep-15.1.0-x86_64-pc-windows-msvc.zip",
      "checksum": "124510B94B6BAA3380D051FDF4650EAA80A302C876D611E9DBA0B2E18D87493A",
      "algorithm": "sha256"
    },
    {
      "id": "github_release/github.com/BurntSushi/ripgrep/15.1.0/ripgrep-15.1.0-x86_64-unknown-linux-musl.tar.gz",
      "checksum": "1C9297BE4A084EEA7ECAEDF93EB03D058D6FAAE29BBC57ECDAF5063921491599",
      "algorithm": "sha256"
    },
    {
      "id": "github_release/github.com/Wilfred/difftastic/0.68.0/difft-aarch64-apple-darwin.tar.gz",
      "checksum": "35DF7904AF1C1AEC9570F08E1A7825301EE317F3131B6B4EDBF3F6D8D209CD8C",
      "algorithm": "sha256"
    },
    {
      "id": "github_release/github.com/Wilfred/difftastic/0.68.0/difft-aarch64-unknown-linux-gnu.tar.gz",
      "checksum": "FAADFB3A88C194033449092FAD3A86F1179738A0B3BFC44580C83473BDB17451",
      "algorithm": "sha256"
    },
    {
      "id": "github_release/github.com/Wilfred/difftastic/0.68.0/difft-x86_64-apple-darwin.tar.gz",
      "checksum": "9C727343FD0FC0504CB004B6619358E5446324E09562FB8E39D66BC82E680070",
      "algorithm": "sha256"
    },
    {
      "id": "github_release/github.com/Wilfred/difftastic/0.68.0/difft-x86_64-pc-windows-msvc.zip",
      "checksum": "A87429EBC75343C9731DEBFD083B954BBD1E87011F962078B9ADE92E33440348",
      "algorithm": "sha256"
    },
    {
      "id": "github_release/github.com/Wilfred/difftastic/0.68.0/difft-x86_64-unknown-linux-musl.tar.gz",
      "checksum": "C242D19DD36DECA88DA9792AB81781BABC309C4F3E9CCC8CE8B3A175B52E7B16",
      "algorithm": "sha256"
    },
    {
      "id": "github_release/github.com/ajeetdsouza/zoxide/v0.9.9/zoxide-0.9.9-aarch64-apple-darwin.tar.gz",
      "checksum": "57E733D0436309DAE2ED97E46BBA43937209395298E1D88812D4E893900CB40A",
      "algorithm": "sha256"
    },
    {
      "id": "github_release/github.com/ajeetdsouza/zoxide/v0.9.9/zoxide-0.9.9-aarch64-pc-windows-msvc.zip",
      "checksum": "58C55EF6F0EAD099FBB31ED69566118D7C7C7A4E16C858BBDB4F7DEF40CD534B",
      "algorithm": "sha256"
    },
    {
      "id": "github_release/github.com/ajeetdsouza/zoxide/v0.9.9/zoxide-0.9.9-aarch64-unknown-linux-musl.tar.gz",
      "checksum": "96E6EA2E47A71DB42CB7AD5A36E9209C8CB3708F8AE00F6945573D0D93315CB0",
      "algorithm": "sha256"
    },
    {
      "id": "github_release/github.com/ajeetdsouza/zoxide/v0.9.9/zoxide-0.9.9-x86_64-apple-darwin.tar.gz",
      "checksum": "364249CFF18354397C72EBB6B8F7358404C051C486E0F2F7A46E36C86C16F8C7",
      "algorithm": "sha256"
    },
    {
      "id": "github_release/github.com/ajeetdsouza/zoxide/v0.9.9/zoxide-0.9.9-x86_64-pc-windows-msvc.zip",
      "checksum": "5AF00D0916F05631E3030537289EAC56605E7C1733318C4D525C8E847F12496D",
      "algorithm": "sha256"
    },
    {
      "id": "github_release/github.com/ajeetdsouza/zoxide/v0.9.9/zoxide-0.9.9-x86_64-unknown-linux-musl.tar.gz",
      "checksum": "4FF057D3C4D957946937274C2B8BE7AF2A9BBAE7F90A1B5E9BAAA7CB65A20CAA",
      "algorithm": "sha256"
    },
    {
      "id": "github_release/github.com/altsem/gitu/v0.41.0/gitu-v0.41.0-aarch64-apple-darwin.zip",
      "checksum": "FF4E01AE9D09074C5E615929AEA13C1C0E04C4ABDB49FA0E8D278DFD1AC0CB31",
      "algorithm": "sha256"
    },
    {
      "id": "github_release/github.com/altsem/gitu/v0.41.0/gitu-v0.41.0-x86_64-apple-darwin.zip",
      "checksum": "C3900EA34EC858901DECF7A25D2E3FBAA3B9CCA8BA3437F777139B83E9EB7ED9",
      "algorithm": "sha256"
    },
    {
      "id": "github_release/github.com/altsem/gitu/v0.41.0/gitu-v0.41.0-x86_64-pc-windows-msvc.zip",
      "checksum": "7A29BBB273EA28A181226794FD60DD00470E7AE104AFDB7CDCAFA86438855B02",
      "algorithm": "sha256"
    },
    {
      "id": "github_release/github.com/altsem/gitu/v0.41.0/gitu-v0.41.0-x86_64-unknown-linux-gnu.zip",
      "checksum": "2D0B111A2AE5AE9C5AF8AA734B57835EA041F9755E67BF0875F30E0B2EA42925",
      "algorithm": "sha256"
    },
    {
      "id": "github_release/github.com/anomalyco/opencode/v1.14.17/opencode-darwin-arm64.zip",
      "checksum": "5BB383CC3FD744F4D1993E18955A4B2BEBB181EF7FECA4260D5B1CB32AF5E3DD",
      "algorithm": "sha256"
    },
    {
      "id": "github_release/github.com/anomalyco/opencode/v1.14.17/opencode-darwin-x64.zip",
      "checksum": "1A021C4B5C97C754D50016880A8517DA1BA1738805C457FABF4A7D0FEC6F6996",
      "algorithm": "sha256"
    },
    {
      "id": "github_release/github.com/anomalyco/opencode/v1.14.17/opencode-linux-arm64.tar.gz",
      "checksum": "73A2C63D2B37DF7A180E4CE51554BC65397EDC5EF837C868420C13E22BA8CDA5",
      "algorithm": "sha256"
    },
    {
      "id": "github_release/github.com/anomalyco/opencode/v1.14.17/opencode-linux-x64.tar.gz",
      "checksum": "DAE7B74B5E0A5928EE4C93C1AA52A3A6F20252E3E49A26CCAF898539E38041D6",
      "algorithm": "sha256"
    },
    {
      "id": "github_release/github.com/anomalyco/opencode/v1.14.17/opencode-windows-x64.zip",
      "checksum": "09650B0EE2CF0E4A97395FB99547DBB9D02955077A6EB7BA3D2001332AF1942E",
      "algorithm": "sha256"
    },
    {
      "id": "github_release/github.com/astral-sh/uv/0.11.7/uv-aarch64-apple-darwin.tar.gz",
      "checksum": "66E37D91F839E12481D7B932A1ECCBFE732560F42C1CFB89FADDFA2454534BA8",
      "algorithm": "sha256"
    },
    {
      "id": "github_release/github.com/astral-sh/uv/0.11.7/uv-aarch64-unknown-linux-musl.tar.gz",
      "checksum": "46647DC16CBB7D6700F762FDD7A67D220ABE18570914732BC310ADC91308D272",
      "algorithm": "sha256"
    },
    {
      "id": "github_release/github.com/astral-sh/uv/0.11.7/uv-x86_64-apple-darwin.tar.gz",
      "checksum": "0A4BC8FCDE4974EA3560BE21772AEECAB600A6F43FA6E58169F9FA7B3B71D302",
      "algorithm": "sha256"
    },
    {
      "id": "github_release/github.com/astral-sh/uv/0.11.7/uv-x86_64-pc-windows-msvc.zip",
      "checksum": "FE0C7815ACF4FC45F8A5EFF58ED3CF7AE2E15C3CF1DCEADBD10C816EC1690CC1",
      "algorithm": "sha256"
    },
    {
      "id": "github_release/github.com/astral-sh/uv/0.11.7/uv-x86_64-unknown-linux-musl.tar.gz",
      "checksum": "64DDB5F1087649E3F75AA50D139AA4F36DDDE728A5295A141E0FA9697BFB7B0F",
      "algorithm": "sha256"
    },
    {
      "id": "github_release/github.com/atuinsh/atuin/v18.15.2/atuin-aarch64-apple-darwin.tar.gz",
      "checksum": "D73608ADE168B24A29DDFED119896EB95FF7F5ADDCD01CAB3BFFF3C93DEEEEE1",
      "algorithm": "sha256"
    },
    {
      "id": "github_release/github.com/atuinsh/atuin/v18.15.2/atuin-aarch64-unknown-linux-musl.tar.gz",
      "checksum": "FE28CEB65BF382F987634D5CAFC12F2FD323D4F4D0CAFC765E0D111815799E87",
      "algorithm": "sha256"
    },
    {
      "id": "github_release/github.com/atuinsh/atuin/v18.15.2/atuin-x86_64-pc-windows-msvc.zip",
      "checksum": "24E0586A5AB477AA7154FB297786C4C9AB4DD1A9D6A873D88692B6E8F981DED7",
      "algorithm": "sha256"
    },
    {
      "id": "github_release/github.com/atuinsh/atuin/v18.15.2/atuin-x86_64-unknown-linux-musl.tar.gz",
      "checksum": "84C76AD3E61CB0A3CDBDCC768374D4BCC400E4A8F376D1302C37059D0D9AFFB1",
      "algorithm": "sha256"
    },
    {
      "id": "github_release/github.com/biomejs/biome/@biomejs/biome@2.3.8/biome-darwin-arm64",
      "checksum": "A7D005E3263322FEAE3EC5D1AA41C14DFE047A537B42E06AB3D1BE2314B91C82",
      "algorithm": "sha256"
    },
    {
      "id": "github_release/github.com/biomejs/biome/@biomejs/biome@2.3.8/biome-darwin-x64",
      "checksum": "C41B74A3A0D8642D09A6B4B7182FA2DE3184228EDFF8F1D2891AB557C2EB6B11",
      "algorithm": "sha256"
    },
    {
      "id": "github_release/github.com/biomejs/biome/@biomejs/biome@2.3.8/biome-linux-arm64",
      "checksum": "96B079189B84F7B203C0A62CFA86B9809E1E8708728FDDDF93FBC8B446DA23FA",
      "algorithm": "sha256"
    },
    {
      "id": "github_release/github.com/biomejs/biome/@biomejs/biome@2.3.8/biome-linux-x64",
      "checksum": "ECD33E78A264395596C8B1C2849AF04C719EE5BCD05E6A52643D836022C034A3",
      "algorithm": "sha256"
    },
    {
      "id": "github_release/github.com/biomejs/biome/@biomejs/biome@2.3.8/biome-win32-arm64.exe",
      "checksum": "D7E1B57393FE72AB390C91950119C129F82C86FF083FD43BC3E86FC674B7B5AE",
      "algorithm": "sha256"
    },
    {
      "id": "github_release/github.com/biomejs/biome/@biomejs/biome@2.3.8/biome-win32-x64.exe",
      "checksum": "E1F3AFC0C5EE0DE0C642C198DFA4D380D7C1A0003E370FBE7ED6A083E3985552",
      "algorithm": "sha256"
    },
    {
      "id": "github_release/github.com/dandavison/delta/0.19.2/delta-0.19.2-aarch64-apple-darwin.tar.gz",
      "checksum": "9BE36612A5A13E9E386DC498FB8E50DC87C72EE42B63DB0EA05B32F99A72A69A",
      "algorithm": "sha256"
    },
    {
      "id": "github_release/github.com/dandavison/delta/0.19.2/delta-0.19.2-aarch64-unknown-linux-gnu.tar.gz",
      "checksum": "0BFCE159A5CDDD5FEB3D6DB4A616D883FF51253CE08AC7EC11CB1D208CFAAB9E",
      "algorithm": "sha256"
    },
    {
      "id": "github_release/github.com/dandavison/delta/0.19.2/delta-0.19.2-x86_64-pc-windows-msvc.zip",
      "checksum": "AC8EBB4A9F1CBEE8B9EA897BA119808A244181ADAE6F3BED1F3B6B923C50B557",
      "algorithm": "sha256"
    },
    {
      "id": "github_release/github.com/dandavison/delta/0.19.2/delta-0.19.2-x86_64-unknown-linux-musl.tar.gz",
      "checksum": "F1EA01CA7728CE3462DEBC359F39DFC7CBBC1A63224B71FEFABF92042864AA1B",
      "algorithm": "sha256"
    },
    {
      "id": "github_release/github.com/denoland/deno/v2.7.12/deno-aarch64-apple-darwin.zip",
      "checksum": "4694916ACF93954611339618F19DFEC01D8128D9A11402838E65BE76E572BC5E",
      "algorithm": "sha256"
    },
    {
      "id": "github_release/github.com/denoland/deno/v2.7.12/deno-aarch64-unknown-linux-gnu.zip",
      "checksum": "4116C1BB5FA2BBA348A1F89C5392D5ECDBB505DD7166796870660556EA6C6C53",
      "algorithm": "sha256"
    },
    {
      "id": "github_release/github.com/denoland/deno/v2.7.12/deno-x86_64-apple-darwin.zip",
      "checksum": "B303D779F20B9CE01355E65430CD9BF921B3B34FA04BDE01E1CCEA05F180FDDC",
      "algorithm": "sha256"
    },
    {
      "id": "github_release/github.com/denoland/deno/v2.7.12/deno-x86_64-pc-windows-msvc.zip",
      "checksum": "F0DB746796FF2155444E4B6B42B24FF1139882626E2CDC3943743A7980F4BC2A",
      "algorithm": "sha256"
    },
    {
      "id": "github_release/github.com/denoland/deno/v2.7.12/deno-x86_64-unknown-linux-gnu.zip",
      "checksum": "4646EC32B4296FDF963A62A3DF3D57E342A3C70376976E5690C34D42E23A3080",
      "algorithm": "sha256"
    },
    {
      "id": "github_release/github.com/docker/compose/v5.1.3/docker-compose-darwin-aarch64",
      "checksum": "B8461A8A53F7E0CE677139516B17661E7CCD54AC4F2DABAE03AD79F2F2AE35C6",
      "algorithm": "sha256"
    },
    {
      "id": "github_release/github.com/docker/compose/v5.1.3/docker-compose-darwin-x86_64",
      "checksum": "F11139D9822CE1F3843E16ED6C2E44BA5525423396C82FA22B08874B26ABD102",
      "algorithm": "sha256"
    },
    {
      "id": "github_release/github.com/docker/compose/v5.1.3/docker-compose-linux-aarch64",
      "checksum": "E8105A3E687EA7E0B0F81ABE4BF9269C8A2801FB72C2B498B5FF2472BC54145F",
      "algorithm": "sha256"
    },
    {
      "id": "github_release/github.com/docker/compose/v5.1.3/docker-compose-linux-x86_64",
      "checksum": "A0298760C9772D2C06888FC8703A487C94C3C3B0134ADEEF830742A2FC7647B4",
      "algorithm": "sha256"
    },
    {
      "id": "github_release/github.com/docker/compose/v5.1.3/docker-compose-windows-aarch64.exe",
      "checksum": "9BDABC5FB175161B93C41B2CE6464B816F8D2614E6B9641F5E0FDF20B188F4A2",
      "algorithm": "sha256"
    },
    {
      "id": "github_release/github.com/docker/compose/v5.1.3/docker-compose-windows-x86_64.exe",
      "checksum": "5E6D72612B3165BE9FEA4AE889435FEC76979A9779B6F62F4EFEE99DD5F41EA1",
      "algorithm": "sha256"
    },
    {
      "id": "github_release/github.com/duckdb/duckdb/v1.5.2/duckdb_cli-linux-amd64.zip",
      "checksum": "FC9145AFFABCA627431E73DDAF6B8117E5C192692480C13886F227BE202D5D15",
      "algorithm": "sha256"
    },
    {
      "id": "github_release/github.com/duckdb/duckdb/v1.5.2/duckdb_cli-linux-arm64.zip",
      "checksum": "28B15A8D78E6DF62F6EC43DA6B0E6397DCD28E25AB93D847DF3C5C97F59375F5",
      "algorithm": "sha256"
    },
    {
      "id": "github_release/github.com/duckdb/duckdb/v1.5.2/duckdb_cli-osx-universal.zip",
      "checksum": "DE789904E1B0B5F305D31B88A6FD8BD4F6ED3F63A00D95F8C7A2559A0995A2F1",
      "algorithm": "sha256"
    },
    {
      "id": "github_release/github.com/duckdb/duckdb/v1.5.2/duckdb_cli-windows-amd64.zip",
      "checksum": "D7B4F5774419C2E9EB14CB7361D3488821EF0244F8AF461FD2C6FCB6F43BC3E0",
      "algorithm": "sha256"
    },
    {
      "id": "github_release/github.com/duckdb/duckdb/v1.5.2/duckdb_cli-windows-arm64.zip",
      "checksum": "7908E22D25E6991F45E895B1613277E2A600EEC6721253F45CE10CDE6A3FFDAF",
      "algorithm": "sha256"
    },
    {
      "id": "github_release/github.com/eza-community/eza/v0.23.4/eza.exe_x86_64-pc-windows-gnu.tar.gz",
      "checksum": "4D4F87F6BC8E6EE176789C28BEE698234CE0275DA013709EB16B0F14819C1688",
      "algorithm": "sha256"
    },
    {
      "id": "github_release/github.com/eza-community/eza/v0.23.4/eza_aarch64-unknown-linux-gnu.tar.gz",
      "checksum": "366E8430225F9955C3DC659B452150C169894833CCFEF455E01765E265A3EDDA",
      "algorithm": "sha256"
    },
    {
      "id": "github_release/github.com/eza-community/eza/v0.23.4/eza_x86_64-unknown-linux-musl.tar.gz",
      "checksum": "D231BB3EE33B08C76279B5888845DCEB7034D055C42BB9BE46DBE0DAE39394DF",
      "algorithm": "sha256"
    },
    {
      "id": "github_release/github.com/github/copilot-cli/v1.0.32/copilot-darwin-arm64.tar.gz",
      "checksum": "F0BCE5E8925CD6DA51D613BD82FFDC93ECD1CB8CCEEFF89E2F07E7A6980AB0B3",
      "algorithm": "sha256"
    },
    {
      "id": "github_release/github.com/github/copilot-cli/v1.0.32/copilot-darwin-x64.tar.gz",
      "checksum": "7C663C6A19329895C095C44481507C524202B67DF33F9DB0D4B86EAFE17B2DA6",
      "algorithm": "sha256"
    },
    {
      "id": "github_release/github.com/github/copilot-cli/v1.0.32/copilot-linux-arm64.tar.gz",
      "checksum": "F6C9D1F8C0BC11911265D7BFC51436F33F21FF9BD314331BA009BAD203A38A59",
      "algorithm": "sha256"
    },
    {
      "id": "github_release/github.com/github/copilot-cli/v1.0.32/copilot-linux-x64.tar.gz",
      "checksum": "2B4507E03B013692A7CA99CE5A3C95045FED2901510BF49ED3A440D5E64FB773",
      "algorithm": "sha256"
    },
    {
      "id": "github_release/github.com/github/copilot-cli/v1.0.32/copilot-win32-arm64.zip",
      "checksum": "C941BE14235699A72D4075A1F2A44C8308884A90F8AF6FEBA9302DC771333882",
      "algorithm": "sha256"
    },
    {
      "id": "github_release/github.com/github/copilot-cli/v1.0.32/copilot-win32-x64.zip",
      "checksum": "FF8CB544A200B24729D2DDC6FEECABF05680F1089E084831E2504F55AB99086C",
      "algorithm": "sha256"
    },
    {
      "id": "github_release/github.com/gitui-org/gitui/v0.28.1/gitui-linux-aarch64.tar.gz",
      "checksum": "2A640DA05B73E9152A7BF92BFD7C23ACD9D60438F4F2CABB62357014A5FD7C28",
      "algorithm": "sha256"
    },
    {
      "id": "github_release/github.com/gitui-org/gitui/v0.28.1/gitui-linux-x86_64.tar.gz",
      "checksum": "F6149B9AE203397158B0C89C13CFDE718E7121D3D3CD2EBC597F93D6628D9B5B",
      "algorithm": "sha256"
    },
    {
      "id": "github_release/github.com/gitui-org/gitui/v0.28.1/gitui-mac.tar.gz",
      "checksum": "3B519A593383841289361BACF579D4A222169AA7EBBDEAE6CC449D488D8BB967",
      "algorithm": "sha256"
    },
    {
      "id": "github_release/github.com/gitui-org/gitui/v0.28.1/gitui-win.tar.gz",
      "checksum": "FAB116CCDF9AE4E17378DB912D76CC26E60AEFD2226F44E665120DEA166867E4",
      "algorithm": "sha256"
    },
    {
      "id": "github_release/github.com/jqlang/jq/jq-1.8.1/jq-linux-amd64",
      "checksum": "020468DE7539CE70EF1BCEAF7CDE2E8C4F2CA6C3AFB84642AABC5C97D9FC2A0D",
      "algorithm": "sha256"
    },
    {
      "id": "github_release/github.com/jqlang/jq/jq-1.8.1/jq-linux-arm64",
      "checksum": "6BC62F25981328EDD3CFCFE6FE51B073F2D7E7710D7EF7FCDAC28D4E384FC3D4",
      "algorithm": "sha256"
    },
    {
      "id": "github_release/github.com/jqlang/jq/jq-1.8.1/jq-macos-amd64",
      "checksum": "E80DBE0D2A2597E3C11C404F03337B981D74B4A8504B70586C354B7697A7C27F",
      "algorithm": "sha256"
    },
    {
      "id": "github_release/github.com/jqlang/jq/jq-1.8.1/jq-macos-arm64",
      "checksum": "A9FE3EA2F86DFC72F6728417521EC9067B343277152B114F4E98D8CB0E263603",
      "algorithm": "sha256"
    },
    {
      "id": "github_release/github.com/jqlang/jq/jq-1.8.1/jq-windows-amd64.exe",
      "checksum": "23CB60A1354EED6BCC8D9B9735E8C7B388CD1FDCB75726B93BC299EF22DD9334",
      "algorithm": "sha256"
    },
    {
      "id": "github_release/github.com/junegunn/fzf/v0.71.0/fzf-0.71.0-darwin_amd64.tar.gz",
      "checksum": "144E98EE6BCFFAF915366162768000561CD2DB8FB53B119D73110391A8E5B5F0",
      "algorithm": "sha256"
    },
    {
      "id": "github_release/github.com/junegunn/fzf/v0.71.0/fzf-0.71.0-darwin_arm64.tar.gz",
      "checksum": "02DFB11DE8773CB79AA4FC5BFC77E75C6604EE14728BC849FC162DD91A9714C4",
      "algorithm": "sha256"
    },
    {
      "id": "github_release/github.com/junegunn/fzf/v0.71.0/fzf-0.71.0-linux_amd64.tar.gz",
      "checksum": "22639BB38489DBCA8ACEF57850CBB50231AB714D0E8E855AC52FAE8B41233DF4",
      "algorithm": "sha256"
    },
    {
      "id": "github_release/github.com/junegunn/fzf/v0.71.0/fzf-0.71.0-linux_arm64.tar.gz",
      "checksum": "98B7D322EFAE9C37E4BFBBAB1CBCD8722EB742D9399511F96375FEB40CC35D1D",
      "algorithm": "sha256"
    },
    {
      "id": "github_release/github.com/junegunn/fzf/v0.71.0/fzf-0.71.0-windows_amd64.zip",
      "checksum": "15BF30FA658C596D740F0CE9A9A97B6B5D90566124903657D09FD109DD0973D2",
      "algorithm": "sha256"
    },
    {
      "id": "github_release/github.com/junegunn/fzf/v0.71.0/fzf-0.71.0-windows_arm64.zip",
      "checksum": "9D0DE41E8C40E8A7AC1EDB64FE93AAE96181ED93439E9E6D8D35DEDA61EE910B",
      "algorithm": "sha256"
    },
    {
      "id": "github_release/github.com/kubernetes-sigs/kind/v0.31.0/kind-darwin-amd64",
      "checksum": "A8B3CF77B2AD77AEC5BF710D1A2589D9117576132AF812885CAD41E9DEDE4D4E",
      "algorithm": "sha256"
    },
    {
      "id": "github_release/github.com/kubernetes-sigs/kind/v0.31.0/kind-darwin-arm64",
      "checksum": "88BF554FE9DA6311C9F8C2D082613C002911A476F6B5090E9420B35D84E70C5C",
      "algorithm": "sha256"
    },
    {
      "id": "github_release/github.com/kubernetes-sigs/kind/v0.31.0/kind-linux-amd64",
      "checksum": "EB244CBAFCC157DFF60CF68693C14C9A75C4E6E6FEDAF9CD71C58117CB93E3FA",
      "algorithm": "sha256"
    },
    {
      "id": "github_release/github.com/kubernetes-sigs/kind/v0.31.0/kind-linux-arm64",
      "checksum": "8E1014E87C34901CC422A1445866835D1E666F2A61301C27E722BDEAB5A1F7E4",
      "algorithm": "sha256"
    },
    {
      "id": "github_release/github.com/kubernetes-sigs/kind/v0.31.0/kind-windows-amd64",
      "checksum": "2C3A9FF954DE16244380778683CF99E271BFC2FAC9C6C4E797E4623C45E59D9D",
      "algorithm": "sha256"
    },
    {
      "id": "github_release/github.com/mikefarah/yq/v4.53.2/yq_darwin_amd64",
      "checksum": "616B0A0F6A5B79D746F05A169C2B9BB40DEE00C605EF165B9A1C1681BBA738AC",
      "algorithm": "sha256"
    },
    {
      "id": "github_release/github.com/mikefarah/yq/v4.53.2/yq_darwin_arm64",
      "checksum": "541BA2287560DF70F561955E2D7F7E1CD00CF2A15A884F6B5C87A4BFA887BC07",
      "algorithm": "sha256"
    },
    {
      "id": "github_release/github.com/mikefarah/yq/v4.53.2/yq_linux_amd64",
      "checksum": "D56BF5C6819E8E696340C312BD70F849DC1678A7CDA9C2AD63EEBD906371D56B",
      "algorithm": "sha256"
    },
    {
      "id": "github_release/github.com/mikefarah/yq/v4.53.2/yq_linux_arm64",
      "checksum": "03061B2A50C7A498DE2BBB92D7CB078CE433011F085A4994117C2726BE4106EA",
      "algorithm": "sha256"
    },
    {
      "id": "github_release/github.com/mikefarah/yq/v4.53.2/yq_windows_amd64.exe",
      "checksum": "2AEE32F1DE46A20672F48C25DF3018839798BD509143F2CE05FDAB1550FF5592",
      "algorithm": "sha256"
    },
    {
      "id": "github_release/github.com/natecraddock/zf/0.10.2/zf-0.10.2-aarch64-linux.tar.xz",
      "checksum": "69AD2AEC6B003D53B5ED60B8E7E0727491BA96716D770A06A9FD2D7CA6B3654C",
      "algorithm": "sha256"
    },
    {
      "id": "github_release/github.com/natecraddock/zf/0.10.2/zf-0.10.2-aarch64-macos.tar.xz",
      "checksum": "024F8EAEFDE05ADF5B10D222A8934C3F9A57E69617D8AB4E2AB418A91BA771E6",
      "algorithm": "sha256"
    },
    {
      "id": "github_release/github.com/natecraddock/zf/0.10.2/zf-0.10.2-x86_64-linux.tar.xz",
      "checksum": "7287C1255D5617069C0463CBCAB910A1C39D1047A1A0BAEA9016E7D9D29C63BE",
      "algorithm": "sha256"
    },
    {
      "id": "github_release/github.com/natecraddock/zf/0.10.2/zf-0.10.2-x86_64-macos.tar.xz",
      "checksum": "69E58D8E2B1B6C7951C360415093E7FB281D164B4DA9EAE50375852E0D71F94F",
      "algorithm": "sha256"
    },
    {
      "id": "github_release/github.com/nushell/nushell/0.112.2/nu-0.112.2-aarch64-apple-darwin.tar.gz",
      "checksum": "A61806761DB7BC2EDDFC313D5EC496C92776A37124BC64A3036374BD55E8C881",
      "algorithm": "sha256"
    },
    {
      "id": "github_release/github.com/nushell/nushell/0.112.2/nu-0.112.2-aarch64-unknown-linux-gnu.tar.gz",
      "checksum": "C25A713F4C10BD886162C62C278DB6CF8A657754BE53D33379AF70FBADAB07B8",
      "algorithm": "sha256"
    },
    {
      "id": "github_release/github.com/nushell/nushell/0.112.2/nu-0.112.2-x86_64-apple-darwin.tar.gz",
      "checksum": "8DE1DC4A918A1AF29FCE75D263A8F673F16D35C04EBAA5E3C3AC4CE1EB154F3F",
      "algorithm": "sha256"
    },
    {
      "id": "github_release/github.com/nushell/nushell/0.112.2/nu-0.112.2-x86_64-pc-windows-msvc.zip",
      "checksum": "DB57750EC878365135E7BAEBEE9F5EC74B84C80158ED0168F1CCBE15D6EC251D",
      "algorithm": "sha256"
    },
    {
      "id": "github_release/github.com/nushell/nushell/0.112.2/nu-0.112.2-x86_64-unknown-linux-musl.tar.gz",
      "checksum": "D9C0BA0938BEED6148C8A354C45612C0979D7A787794B8DD13E866CA3B571375",
      "algorithm": "sha256"
    },
    {
      "id": "github_release/github.com/oven-sh/bun/bun-v1.3.12/bun-darwin-aarch64.zip",
      "checksum": "6C4BB87DD013ED1A8D6A16E357A3D094959FD5530B4D7061F7F3680C3C7CEA1C",
      "algorithm": "sha256"
    },
    {
      "id": "github_release/github.com/oven-sh/bun/bun-v1.3.12/bun-darwin-x64.zip",
      "checksum": "0F58C53A3E7947F1E626D2F8D285F97C14B7CADCCA9C09EBAFC0AE9D35B58C3D",
      "algorithm": "sha256"
    },
    {
      "id": "github_release/github.com/oven-sh/bun/bun-v1.3.12/bun-linux-aarch64.zip",
      "checksum": "C40BC0EBCA11BDE7D75AF497A654A874D0C7FD8D6A8D6031C173C10C9064297B",
      "algorithm": "sha256"
    },
    {
      "id": "github_release/github.com/oven-sh/bun/bun-v1.3.12/bun-linux-x64.zip",
      "checksum": "11DC3EE11BC1695E149737C6CA3D5619302CF4346E6B8A6EC7988967EF01DDC5",
      "algorithm": "sha256"
    },
    {
      "id": "github_release/github.com/oven-sh/bun/bun-v1.3.12/bun-windows-x64.zip",
      "checksum": "841FF9C5DFFCAA3A2620D1E3F87EE500F32A4CA830B001CADE7A3479609D4A89",
      "algorithm": "sha256"
    },
    {
      "id": "github_release/github.com/rhysd/vim-startuptime/v1.3.2/vim-startuptime_1.3.2_darwin_amd64.tar.gz",
      "checksum": "050D3DE9F35537D73326A6BB0C81E9EAF229E4F63D98218A09C4CD07212760AB",
      "algorithm": "sha256"
    },
    {
      "id": "github_release/github.com/rhysd/vim-startuptime/v1.3.2/vim-startuptime_1.3.2_darwin_arm64.tar.gz",
      "checksum": "1B9D7F178DD025BF87371EAE4C8BC2FABD8CCFD1ED3C820053B975E18B6C35D4",
      "algorithm": "sha256"
    },
    {
      "id": "github_release/github.com/rhysd/vim-startuptime/v1.3.2/vim-startuptime_1.3.2_linux_amd64.tar.gz",
      "checksum": "368FC3734ECFB734CB2D543925D268832FDA675E560315DA50DB4DAF62316D45",
      "algorithm": "sha256"
    },
    {
      "id": "github_release/github.com/rhysd/vim-startuptime/v1.3.2/vim-startuptime_1.3.2_linux_arm64.tar.gz",
      "checksum": "28EE09E727547444EC44B84AA738FA7F41967D89E7D579FEDACD859F9DFBC309",
      "algorithm": "sha256"
    },
    {
      "id": "github_release/github.com/rhysd/vim-startuptime/v1.3.2/vim-startuptime_1.3.2_windows_amd64.zip",
      "checksum": "7C45112E401E25C99DC6C01DD980DAA5F1757F07500DB0BECA576D1A9E2D2843",
      "algorithm": "sha256"
    },
    {
      "id": "github_release/github.com/rhysd/vim-startuptime/v1.3.2/vim-startuptime_1.3.2_windows_arm64.zip",
      "checksum": "EB6BBBAB34FD30A72BDFD0771D2E2C72F1647DB616A9542BD61D9016076F69F7",
      "algorithm": "sha256"
    },
    {
      "id": "github_release/github.com/sharkdp/bat/v0.26.1/bat-v0.26.1-aarch64-apple-darwin.tar.gz",
      "checksum": "E30BEFF26779C9BF60BB541E1D79046250CB74378F2757F8EB250AFDDB19E114",
      "algorithm": "sha256"
    },
    {
      "id": "github_release/github.com/sharkdp/bat/v0.26.1/bat-v0.26.1-aarch64-unknown-linux-musl.tar.gz",
      "checksum": "6369242C584065F195FB20CB36FBD7CB63AE690605BBE89868A7596B596C2C23",
      "algorithm": "sha256"
    },
    {
      "id": "github_release/github.com/sharkdp/bat/v0.26.1/bat-v0.26.1-x86_64-apple-darwin.tar.gz",
      "checksum": "830D63B0BBA1FA040542EC569E3CF77F60D3356B9DE75116A344B061E0894245",
      "algorithm": "sha256"
    },
    {
      "id": "github_release/github.com/sharkdp/bat/v0.26.1/bat-v0.26.1-x86_64-pc-windows-msvc.zip",
      "checksum": "0F729B4B6F5F28D395C641EACC2E9FF68D0096B85AA0EEC344AA62425144B69B",
      "algorithm": "sha256"
    },
    {
      "id": "github_release/github.com/sharkdp/bat/v0.26.1/bat-v0.26.1-x86_64-unknown-linux-musl.tar.gz",
      "checksum": "0DCD8AC79732C0D5B136F11F4EE00E581440E16A44EAB5B3105B611BBF2CF191",
      "algorithm": "sha256"
    },
    {
      "id": "github_release/github.com/sharkdp/fd/v10.4.2/fd-v10.4.2-aarch64-apple-darwin.tar.gz",
      "checksum": "623DC0AFC81B92E4D4606B380D7BC91916BA7B97814263E554D50923A39E480A",
      "algorithm": "sha256"
    },
    {
      "id": "github_release/github.com/sharkdp/fd/v10.4.2/fd-v10.4.2-aarch64-pc-windows-msvc.zip",
      "checksum": "4F9110C2D5B33A7F760BFA5510F4C113D828109F7277D421B1053A9943C0FC92",
      "algorithm": "sha256"
    },
    {
      "id": "github_release/github.com/sharkdp/fd/v10.4.2/fd-v10.4.2-aarch64-unknown-linux-musl.tar.gz",
      "checksum": "F32D3657473FBA74E2600BABC8DB0B93420D51169223B7E8143B2ED55D8FD9E8",
      "algorithm": "sha256"
    },
    {
      "id": "github_release/github.com/sharkdp/fd/v10.4.2/fd-v10.4.2-x86_64-pc-windows-msvc.zip",
      "checksum": "B2816E506390A89941C63C9187D58A3CC10E9A55F2EF0685F9EA0ECCAF7C98C8",
      "algorithm": "sha256"
    },
    {
      "id": "github_release/github.com/sharkdp/fd/v10.4.2/fd-v10.4.2-x86_64-unknown-linux-musl.tar.gz",
      "checksum": "E3257D48E29A6BE965187DBD24CE9AF564E0FE67B3E73C9BDCD180F4EC11BDDE",
      "algorithm": "sha256"
    },
    {
      "id": "github_release/github.com/sharkdp/hyperfine/v1.20.0/hyperfine-v1.20.0-aarch64-unknown-linux-gnu.tar.gz",
      "checksum": "90875CB1DB7A1D797C311174D061728361E58FC70E3B62262A00635AC3B1997C",
      "algorithm": "sha256"
    },
    {
      "id": "github_release/github.com/sharkdp/hyperfine/v1.20.0/hyperfine-v1.20.0-x86_64-apple-darwin.tar.gz",
      "checksum": "F58D0B90993FADFA122A351428C469CE24AFEF3865F027F0E6E86F0830D088F1",
      "algorithm": "sha256"
    },
    {
      "id": "github_release/github.com/sharkdp/hyperfine/v1.20.0/hyperfine-v1.20.0-x86_64-pc-windows-msvc.zip",
      "checksum": "2508C549B049B1D4342D08EDC1CB42BFAC169082B6E3069431B5BAB9822DBB32",
      "algorithm": "sha256"
    },
    {
      "id": "github_release/github.com/sharkdp/hyperfine/v1.20.0/hyperfine-v1.20.0-x86_64-unknown-linux-musl.tar.gz",
      "checksum": "3285EC7959285288137043DD81DCE0DDE056227018A8277532D9A364B4F03C2B",
      "algorithm": "sha256"
    },
    {
      "id": "github_release/github.com/starship/starship/v1.25.0/starship-aarch64-apple-darwin.tar.gz",
      "checksum": "365301B5F4938322A9F378764B4BC640048BCA7D6AC28EAABD406CADD6FC703A",
      "algorithm": "sha256"
    },
    {
      "id": "github_release/github.com/starship/starship/v1.25.0/starship-aarch64-pc-windows-msvc.zip",
      "checksum": "E4FF9ACFAB812759871B842F4B99B461924F0A758DE21B47471C7A5A0F6C6B8E",
      "algorithm": "sha256"
    },
    {
      "id": "github_release/github.com/starship/starship/v1.25.0/starship-aarch64-unknown-linux-musl.tar.gz",
      "checksum": "68FFCB75582E5ED336B43598BB4D8ECC4EC994EA26EAC7955D3D378F1375DA34",
      "algorithm": "sha256"
    },
    {
      "id": "github_release/github.com/starship/starship/v1.25.0/starship-x86_64-apple-darwin.tar.gz",
      "checksum": "05421BFC05ED00394EC4A7EA20213BD9920B2858713CBE1DDF257EBCEBF5DA88",
      "algorithm": "sha256"
    },
    {
      "id": "github_release/github.com/starship/starship/v1.25.0/starship-x86_64-pc-windows-msvc.zip",
      "checksum": "6C21422D1B786ED49937ADCB3F23BEBD169D32FEF9B72AE8E77DC1BDB4C2ACF1",
      "algorithm": "sha256"
    },
    {
      "id": "github_release/github.com/starship/starship/v1.25.0/starship-x86_64-unknown-linux-musl.tar.gz",
      "checksum": "0169F187E927A0EE9ABF41BB80E316717FEA6E37E404267BCA5134C6EA10C0ED",
      "algorithm": "sha256"
    },
    {
      "id": "github_release/github.com/suzuki-shunsuke/pinact/v3.9.0/pinact_darwin_amd64.tar.gz",
      "checksum": "70F68407A05FA88843FBF9B400D979E6205489EF8AF251DACC21841A07989DF4",
      "algorithm": "sha256"
    },
    {
      "id": "github_release/github.com/suzuki-shunsuke/pinact/v3.9.0/pinact_darwin_arm64.tar.gz",
      "checksum": "23C8A4EDA8FD7949C8CBB1CFE6F3D01279402FE6201E9CB0A90447A5ECFDEF89",
      "algorithm": "sha256"
    },
    {
      "id": "github_release/github.com/suzuki-shunsuke/pinact/v3.9.0/pinact_linux_amd64.tar.gz",
      "checksum": "3829DA718DE38B1E914B974C3E77045A256999AF84789437A7305B09130D8A6A",
      "algorithm": "sha256"
    },
    {
      "id": "github_release/github.com/suzuki-shunsuke/pinact/v3.9.0/pinact_linux_arm64.tar.gz",
      "checksum": "34A957423002662C6289782B571660BEDA6A37449A76D763C8AD8B1B9A500A54",
      "algorithm": "sha256"
    },
    {
      "id": "github_release/github.com/suzuki-shunsuke/pinact/v3.9.0/pinact_windows_amd64.zip",
      "checksum": "B923A567F88417D79CE183E59C2A2372D9CAE9B697A472CE1F95D745932746B1",
      "algorithm": "sha256"
    },
    {
      "id": "github_release/github.com/suzuki-shunsuke/pinact/v3.9.0/pinact_windows_arm64.zip",
      "checksum": "A2DBFBA73410063EE683636EE61CD57C43F130B7DF90442A40F5D57734C73A5A",
      "algorithm": "sha256"
    },
    {
      "id": "github_release/github.com/sxyazi/yazi/v26.1.22/yazi-aarch64-apple-darwin.zip",
      "checksum": "8355AD582DD9F4EF1F88A228080F2B6116BBB483DD48D1BDE555D475F4D2AFE4",
      "algorithm": "sha256"
    },
    {
      "id": "github_release/github.com/sxyazi/yazi/v26.1.22/yazi-aarch64-unknown-linux-musl.zip",
      "checksum": "91A37CDB3AA49F903AAB6AF57BCA708935ACB6DEF1D9F218716AB414F0A3A8B1",
      "algorithm": "sha256"
    },
    {
      "id": "github_release/github.com/sxyazi/yazi/v26.1.22/yazi-x86_64-apple-darwin.zip",
      "checksum": "1E097C015A968ABA29BBC11BFFDB99A7AEDAF92C78DF09D00613283DAC0F148C",
      "algorithm": "sha256"
    },
    {
      "id": "github_release/github.com/sxyazi/yazi/v26.1.22/yazi-x86_64-pc-windows-msvc.zip",
      "checksum": "7D6C8E3F596F99DD8F20FC7B806C9195C4746C2B7100D0E90A7FF80C259C899A",
      "algorithm": "sha256"
    },
    {
      "id": "github_release/github.com/sxyazi/yazi/v26.1.22/yazi-x86_64-unknown-linux-musl.zip",
      "checksum": "B977351968206C0B78D2EF5BF21351685CC191B58A4C7E1C98C37DB5D0A381F8",
      "algorithm": "sha256"
    },
    {
      "id": "github_release/github.com/tree-sitter/tree-sitter/v0.26.8/tree-sitter-linux-arm64.gz",
      "checksum": "E339D6533B20830DD1666FE320AFF85D301B3F59964A3836870B77F4827F9A17",
      "algorithm": "sha256"
    },
    {
      "id": "github_release/github.com/tree-sitter/tree-sitter/v0.26.8/tree-sitter-linux-x64.gz",
      "checksum": "9754A32800F0B970152782DF177B4A47C711E34E651A7ACEB384D8BD29FA136E",
      "algorithm": "sha256"
    },
    {
      "id": "github_release/github.com/tree-sitter/tree-sitter/v0.26.8/tree-sitter-macos-arm64.gz",
      "checksum": "024E2CEE34723524D62D41BDE4D2B4AF23C8BBE0236E116C79C0B37D9575889E",
      "algorithm": "sha256"
    },
    {
      "id": "github_release/github.com/tree-sitter/tree-sitter/v0.26.8/tree-sitter-macos-x64.gz",
      "checksum": "D0DAA279054C1D1CEDB08F5CA784B451CEB1F0E6B083B112D07317958AE77FE0",
      "algorithm": "sha256"
    },
    {
      "id": "github_release/github.com/tree-sitter/tree-sitter/v0.26.8/tree-sitter-windows-arm64.gz",
      "checksum": "7E276C740A1D47D3326F2450C91A40165265D4BB3097F5DF584285F8460A307D",
      "algorithm": "sha256"
    },
    {
      "id": "github_release/github.com/tree-sitter/tree-sitter/v0.26.8/tree-sitter-windows-x64.gz",
      "checksum": "28301A969412066BF4818C30C71D9C313091A9B9DC24B53A14DDDA3A8E2CC2BB",
      "algorithm": "sha256"
    },
    {
      "id": "github_release/github.com/x-motemen/ghq/v1.10.1/ghq_darwin_amd64.zip",
      "checksum": "3CA71E44BC393B399ACD0EF039FF2904B7BB9D24",
      "algorithm": "sha1"
    },
    {
      "id": "github_release/github.com/x-motemen/ghq/v1.10.1/ghq_darwin_arm64.zip",
      "checksum": "E65585D6AFD5AD5E27933BB471DC71C64211D267",
      "algorithm": "sha1"
    },
    {
      "id": "github_release/github.com/x-motemen/ghq/v1.10.1/ghq_linux_amd64.zip",
      "checksum": "B0F0CC8775481F2793B58B610616C7612591B488",
      "algorithm": "sha1"
    },
    {
      "id": "github_release/github.com/x-motemen/ghq/v1.10.1/ghq_linux_arm64.zip",
      "checksum": "B9C0CE104F1782D877C1B4F5639B71B9DB911040",
      "algorithm": "sha1"
    },
    {
      "id": "github_release/github.com/x-motemen/ghq/v1.10.1/ghq_windows_amd64.zip",
      "checksum": "A244BC16EC43D7626042D05978FDD9AD9C86BAFE",
      "algorithm": "sha1"
    },
    {
      "id": "github_release/github.com/x-motemen/ghq/v1.10.1/ghq_windows_arm64.zip",
      "checksum": "67F7E45DEB730336ACD539F710C59B8444E92ADD",
      "algorithm": "sha1"
    },
    {
      "id": "http/awscli.amazonaws.com/AWSCLIV2-2.34.32.pkg",
      "checksum": "36B3662FBAC78AD9E036C47CAA3CC47DD77F0358801A1F5F12BBD06B82D65163",
      "algorithm": "sha256"
    },
    {
      "id": "http/awscli.amazonaws.com/awscli-exe-linux-aarch64-2.34.32.zip",
      "checksum": "5456BB34D6A77F1690FB0DB8FBD8AE17CBAB43B21F833AC36E256BC1F716A809",
      "algorithm": "sha256"
    },
    {
      "id": "http/awscli.amazonaws.com/awscli-exe-linux-x86_64-2.34.32.zip",
      "checksum": "AD983363B8286928B37BEC605348255DDC39E73BA2E79A969ED1C034FE2DC8B3",
      "algorithm": "sha256"
    },
    {
      "id": "http/dl.k8s.io/v1.35.4/bin/darwin/amd64/kubectl",
      "checksum": "DDDB01BDDB96F78E48E33105CCFA2FEEDFF585A8B2E3B812F5D0F64C7403710A",
      "algorithm": "sha256"
    },
    {
      "id": "http/dl.k8s.io/v1.35.4/bin/darwin/arm64/kubectl",
      "checksum": "EC644A2473B64B486987F695DFB1867963CE6D42D267B86E944585A546F92B5D",
      "algorithm": "sha256"
    },
    {
      "id": "http/dl.k8s.io/v1.35.4/bin/linux/amd64/kubectl",
      "checksum": "B529430DF69A688FD61B64AD2299EDB5FD71CB58BE2A4779DBA624C7D3510EFD",
      "algorithm": "sha256"
    },
    {
      "id": "http/dl.k8s.io/v1.35.4/bin/linux/arm64/kubectl",
      "checksum": "6A5A4CC4E396D7626A7A693A3044B51C75520F81DB30FE6816C2554E53BE336F",
      "algorithm": "sha256"
    },
    {
      "id": "http/dl.k8s.io/v1.35.4/bin/windows/amd64/kubectl.exe",
      "checksum": "D77D03309BD80DE56DAFE8CA59FF6F2076E2ED4EE61C6A94657A4B6E945210E6",
      "algorithm": "sha256"
    },
    {
      "id": "http/dl.k8s.io/v1.35.4/bin/windows/arm64/kubectl.exe",
      "checksum": "7FC20079BF0E2B67BA3B2F9841BFB15F34D4C828D00BFCE39D3D57C3DCA21FDF",
      "algorithm": "sha256"
    },
    {
      "id": "http/download.docker.com/linux/static/stable/aarch64/docker-27.4.1.tgz",
      "checksum": "4C3A49213419CAC4ABF4C12B601490D37B0768DCD1BC87C4A8BE88A07900F774",
      "algorithm": "sha256"
    },
    {
      "id": "http/download.docker.com/linux/static/stable/x86_64/docker-27.4.1.tgz",
      "checksum": "9DC39FA726DB525F22BD6861308A09F6C31A14DE3E512BA1576A329B833798F5",
      "algorithm": "sha256"
    },
    {
      "id": "http/download.docker.com/mac/static/stable/aarch64/docker-27.4.1.tgz",
      "checksum": "29197DA09AD014AA601D6669CEF8CBC7CE0267FEB18BAF9C1C86D82A2213457F",
      "algorithm": "sha256"
    },
    {
      "id": "http/download.docker.com/mac/static/stable/x86_64/docker-27.4.1.tgz",
      "checksum": "F32785EA4B5AFA321116E65B554D79E96037B524B77A688C20C53B74358C940B",
      "algorithm": "sha256"
    },
    {
      "id": "http/download.docker.com/win/static/stable/x86_64/docker-27.4.1.zip",
      "checksum": "2FBCF76331BD0773BFFC8ABB9B4DF81D29196827F17534196FA43ABB29B1D408",
      "algorithm": "sha256"
    },
    {
      "id": "registries/github_content/github.com/aquaproj/aqua-registry/v4.495.0/registry.yaml",
      "checksum": "F0D0BDFDE9B14E81841D9F947587F25DDBCEEF1185FF5C6552E70290A9344A43F770D9F4A90D244DD6101DC5D4DE47FA7360C650E60185229C8519D0F9942EEB",
      "algorithm": "sha512"
    }
  ]
}
